quicksample.py
quicksample611-0.0.4.dist-info/METADATA
quicksample611-0.0.4.dist-info/WHEEL
quicksample611-0.0.4.dist-info/top_level.txt
quicksample611-0.0.4.dist-info/RECORD
