Metadata-Version: 2.1
Name: quicksample611
Version: 0.0.4
Summary: Quicksample test package
Home-page: UNKNOWN
Author: anis dhouieb
License: UNKNOWN
Platform: UNKNOWN
Classifier: Programming Language :: Python :: 3
Classifier: License :: OSI Approved :: MIT License
Classifier: Operating System :: OS Independent
Requires-Python: >=3.6
